{"status":{"timestamp":"2021-08-11T14:11:30.303Z","error_code":0,"error_message":null,"elapsed":9,"credit_count":1,"notice":null,"total_count":5979},"data":[{"id":1,"name":"Bitcoin","symbol":"BTC","slug":"bitcoin","num_market_pairs":8936,"date_added":"2013-04-28T00:00:00.000Z","tags":["mineable","pow","sha-256","store-of-value","state-channels","coinbase-ventures-portfolio","three-arrows-capital-portfolio","polychain-capital-portfolio","binance-labs-portfolio","arrington-xrp-capital","blockchain-capital-portfolio","boostvc-portfolio","cms-holdings-portfolio","dcg-portfolio","dragonfly-capital-portfolio","electric-capital-portfolio","fabric-ventures-portfolio","framework-ventures","galaxy-digital-portfolio","huobi-capital","alameda-research-portfolio","a16z-portfolio","1confirmation-portfolio","winklevoss-capital","usv-portfolio","placeholder-ventures-portfolio","pantera-capital-portfolio","multicoin-capital-portfolio","paradigm-xzy-screener"],"max_supply":21000000,"circulating_supply":18783031,"total_supply":18783031,"platform":null,"cmc_rank":1,"last_updated":"2021-08-11T14:11:02.000Z","quote":{"BR":{"price":29827175.669931643,"volume_24h":21573794527569.26,"percent_change_1h":0.82127545,"percent_change_24h":-1.47501985,"percent_change_7d":11.00637946,"percent_change_30d":34.76898586,"percent_change_60d":29.43321366,"percent_change_90d":-8.85571338,"market_cap":560244765250771.8,"market_cap_dominance":45.1104,"fully_diluted_market_cap":626370689068564,"last_updated":"2021-08-11T14:11:04.000Z"}}},{"id":1027,"name":"Ethereum","symbol":"ETH","slug":"ethereum","num_market_pairs":5615,"date_added":"2015-08-07T00:00:00.000Z","tags":["mineable","pow","smart-contracts","ethereum","binance-smart-chain","coinbase-ventures-portfolio","three-arrows-capital-portfolio","polychain-capital-portfolio","binance-labs-portfolio","arrington-xrp-capital","blockchain-capital-portfolio","boostvc-portfolio","cms-holdings-portfolio","dcg-portfolio","dragonfly-capital-portfolio","electric-capital-portfolio","fabric-ventures-portfolio","framework-ventures","hashkey-capital-portfolio","kinetic-capital","huobi-capital","alameda-research-portfolio","a16z-portfolio","1confirmation-portfolio","winklevoss-capital","usv-portfolio","placeholder-ventures-portfolio","pantera-capital-portfolio","multicoin-capital-portfolio","paradigm-xzy-screener"],"max_supply":null,"circulating_supply":117062273.5615,"total_supply":117062273.5615,"platform":null,"cmc_rank":2,"last_updated":"2021-08-11T14:11:02.000Z","quote":{"BR":{"price":2090947.859967609,"volume_24h":17875645235104.31,"percent_change_1h":0.93925662,"percent_change_24h":-0.43746851,"percent_change_7d":16.11632584,"percent_change_30d":50.62099981,"percent_change_60d":33.926118,"percent_change_90d":-16.60249774,"market_cap":244771110386361.25,"market_cap_dominance":19.7088,"fully_diluted_market_cap":244771110386363.94,"last_updated":"2021-08-11T14:11:04.000Z"}}},{"id":1839,"name":"Binance Coin","symbol":"BNB","slug":"binance-coin","num_market_pairs":543,"date_added":"2017-07-25T00:00:00.000Z","tags":["marketplace","centralized-exchange","payments","binance-smart-chain","alameda-research-portfolio","multicoin-capital-portfolio"],"max_supply":168137036,"circulating_supply":168137036,"total_supply":168137036,"platform":null,"cmc_rank":3,"last_updated":"2021-08-11T14:11:07.000Z","quote":{"BR":{"price":254503.04747559218,"volume_24h":1550732612606.127,"percent_change_1h":2.24560485,"percent_change_24h":3.36206361,"percent_change_7d":12.2485145,"percent_change_30d":19.1456098,"percent_change_60d":15.00078527,"percent_change_90d":-35.94072529,"market_cap":42791388055513.35,"market_cap_dominance":3.4455,"fully_diluted_market_cap":42791388055513.305,"last_updated":"2021-08-11T14:11:04.000Z"}}},{"id":825,"name":"Tether","symbol":"USDT","slug":"tether","num_market_pairs":16676,"date_added":"2015-02-25T00:00:00.000Z","tags":["payments","stablecoin","stablecoin-asset-backed","binance-smart-chain","avalanche-ecosystem","solana-ecosystem"],"max_supply":null,"circulating_supply":62564734130.548836,"total_supply":64468847059.56271,"platform":{"id":1027,"name":"Ethereum","symbol":"ETH","slug":"ethereum","token_address":"0xdac17f958d2ee523a2206206994597c13d831ec7"},"cmc_rank":4,"last_updated":"2021-08-11T14:11:06.000Z","quote":{"BR":{"price":644.5299747235835,"volume_24h":52225104815010.086,"percent_change_1h":0.32625646,"percent_change_24h":-3.32732204,"percent_change_7d":-6.53797984,"percent_change_30d":-2.34007875,"percent_change_60d":-0.01321287,"percent_change_90d":0.02813578,"market_cap":40324846507750.36,"market_cap_dominance":3.2469,"fully_diluted_market_cap":41552104365757.67,"last_updated":"2021-08-11T14:11:04.000Z"}}},{"id":2010,"name":"Cardano","symbol":"ADA","slug":"cardano","num_market_pairs":284,"date_added":"2017-10-01T00:00:00.000Z","tags":["mineable","dpos","pos","platform","research","smart-contracts","staking","binance-smart-chain"],"max_supply":45000000000,"circulating_supply":32096716232.751,"total_supply":32982237587.058,"platform":null,"cmc_rank":5,"last_updated":"2021-08-11T14:10:07.000Z","quote":{"BR":{"price":1205.0147075025936,"volume_24h":3307972070663.374,"percent_change_1h":4.88836197,"percent_change_24h":15.15227307,"percent_change_7d":28.30097067,"percent_change_30d":36.69955671,"percent_change_60d":28.23143736,"percent_change_90d":3.44631947,"market_cap":38677015123002.195,"market_cap_dominance":3.1142,"fully_diluted_market_cap":54225661837614.266,"last_updated":"2021-08-11T14:11:04.000Z"}}}]}